simmed/.DS_Store
simmed/__init__.py
simmed/baseservice.py
simmed/config.py
simmed/info_base.py
simmed/jsonencoder.py
simmed/nacos_client.py
simmed/pymongos.py
simmed/rpcrequest.py
simmed/rpcresponse.py
simmed/service_dispatcher.py
simmed/simmed_core.py
simmed/simmed_jsonrpc.py
simmed/swagger_gen.py
simmed/zipkin.py
simmed-0.2.8.dist-info/LICENSE
simmed-0.2.8.dist-info/METADATA
simmed-0.2.8.dist-info/WHEEL
simmed-0.2.8.dist-info/top_level.txt
simmed-0.2.8.dist-info/RECORD
