Metadata-Version: 2.1
Name: simmed
Version: 0.2.8
Summary: 微服务基础框架
Home-page: https://simmed.cn
Author: weizw,lijunhua,zhaoyun
Author-email: weizw <weizhuwang@simmed.cn>, defa <lijunnhua@simmed.cn>, zhaoyun <zhaoyun@simmed.cn>
License: Copyright (C) 2022 SimMed
Project-URL: Homepage, https://simmed.cn
Project-URL: Bug Tracker, https://simmed.cn
Keywords: simmed
Platform: any
Classifier: Programming Language :: Python :: 3
Classifier: License :: OSI Approved :: MIT License
Classifier: Operating System :: OS Independent
Requires-Python: >=3.8, <4
License-File: LICENSE
